{"cameraMode":{"drawMode":0,"name":"Shaded","section":"Shading Mode"},"sceneLighting":true,"audioPlay":false,"sceneViewState":{"m_AlwaysRefresh":false,"showFog":true,"showSkybox":true,"showFlares":true,"showImageEffects":true,"showParticleSystems":true,"showVisualEffectGraphs":true,"m_FxEnabled":true},"in2DMode":false,"pivot":{"x":226.20001220703126,"y":216.60000610351563,"z":0.0},"rotation":{"x":0.0005607346538454294,"y":-0.9985907077789307,"z":-0.05336446315050125,"w":-0.010460718534886837},"size":279.50848388671877,"orthographic":false}